{
  "bg": {
    "meta": {
      "title": "Железопътен транспорт | Atlant Logistics",
      "description": "Ефективност на дълги разстояния"
    },
    "hero": {
      "label": "Atlant Logistics",
      "title": "Железопътен транспорт",
      "subtitle": "Ефективност на дълги разстояния"
    },
    "sections": [
      {
        "type": "intro-accent",
        "heading": "Ефективност на дълги разстояния",
        "paragraphs": [
          "Железопътният транспорт е един от най-надеждните и устойчиви методи за превоз на товари, особено на дълги разстояния.",
          "Atlant Logistics & Relocations предлага международен ЖП транспорт за насипни, палетизирани и контейнерирани товари. Подходящ за големи обеми със стабилен график и оптимални разходи. Извършваме комбинирани услуги с автомобили и контейнери при нужда от междинни доставки.",
          "Работим с надеждни европейски и международни ЖП оператори, осигурявайки проследимост, сигурност и екологично предимство."
        ]
      },
      {
        "type": "service-topics",
        "label": "Полезни съвети",
        "heading": "Всичко, което трябва да знаете за Железопътен транспорт",
        "topics": [
          {
            "title": "Особености при планирането на ЖП превози",
            "intro": "ЖП транспортът има своя логика, различна от „поръчвам камион за утре“:",
            "points": [
              {
                "title": "Графици и слотове",
                "text": "Работи с графици и слотове, които се планират предварително."
              },
              {
                "title": "Подходящо оборудване",
                "text": "Нуждае се от подходящо оборудване за товарене/разтоварване – рампи, кранове, силози, конвейери според типа товар."
              },
              {
                "title": "Международни оператори",
                "text": "Често включва международни оператори, чиито изисквания трябва да се синхронизират (документи, изисквания за опаковка, безопасност)."
              }
            ],
            "footer": [
              "Добре планираният ЖП превоз може да донесе сериозна икономия, но изисква компетентен партньор, който познава мрежата и процедурите."
            ]
          },
          {
            "title": "Разходи при ЖП транспорт: къде реално се пести и къде не",
            "intro": "Често ЖП транспортът се възприема просто като „по-евтин от камион“. Реалността е малко по-пипкава:",
            "points": [
              {
                "title": "Къде е икономията",
                "text": "При големи обеми – цели вагони или блок-влакове."
              },
              {
                "title": "Дълги разстояния",
                "text": "При дълги разстояния, където цената на тон/километър пада значително спрямо автомобилен превоз."
              },
              {
                "title": "Регулярни графици",
                "text": "При регулярни графици, когато може да се планира натовареността и да се договорят по-добри тарифи."
              },
              {
                "title": "Къде има скрити разходи, ако не се внимава",
                "text": "Товаро-разтоварни операции на терминали (ЖП → камион и обратно)."
              },
              {
                "title": "Такси за престой",
                "text": "Такси за престой, ако документите не са изрядни или няма готовност за приемане на стоката."
              },
              {
                "title": "Неоптимизирани партиди",
                "text": "Неоптимизирани партиди – твърде малки количества, „набутани“ насила в ЖП схема, вместо да останат на камион."
              }
            ],
            "footer": []
          }
        ]
      },
      {
        "type": "comparison-table",
        "label": "Сравнение",
        "heading": "Предимства на ЖП vs. Автомобилен транспорт в таблица",
        "columns": [
          "Критерий",
          "Железопътен транспорт (ЖП)",
          "Автомобилен транспорт"
        ],
        "rows": [
          {
            "criterion": "Цена на превоз",
            "left": "По-ниска при големи обеми и дълги разстояния",
            "right": "По-висока, особено при големи разстояния"
          },
          {
            "criterion": "Капацитет и обем",
            "left": "Подходящ за големи и тежки товари (насипни, контейнери, цистерни)",
            "right": "Ограничен от товароносимостта на камиона и пътната инфраструктура"
          },
          {
            "criterion": "Енергийна ефективност",
            "left": "По-ефективен и екологичен (по-нисък разход на гориво/тон-километър)",
            "right": "По-голям разход на гориво и емисии CO₂"
          },
          {
            "criterion": "Надеждност и предсказуемост",
            "left": "Висока при дълги разстояния и фиксирани маршрути",
            "right": "Зависим от трафик, пътни условия и регулации"
          },
          {
            "criterion": "Въздействие върху околната среда",
            "left": "По-ниско (по-малко шум, по-малко емисии)",
            "right": "Високо замърсяване и шум в градски зони"
          },
          {
            "criterion": "Подходящ за видове товари",
            "left": "Насипни, контейнери, суровини, тежки машини",
            "right": "Палетизирани, дребни пратки, бързоразвалящи се стоки"
          },
          {
            "criterion": "Международен транспорт",
            "left": "Отличен за транзит и големи обеми по определени коридори (TEN-T)",
            "right": "Гъвкав, но ограничен от митници, трафик и ограничения по пътищата"
          },
          {
            "criterion": "Сигурност на товара",
            "left": "Висока – по-малко произшествия и кражби",
            "right": "По-ниска – по-чести пътни инциденти и рискове при превоз"
          }
        ]
      }
    ]
  },
  "en": {
    "meta": {
      "title": "Rail Transport | Atlant Logistics",
      "description": "Long-Distance Efficiency"
    },
    "hero": {
      "label": "Atlant Logistics",
      "title": "Rail Transport",
      "subtitle": "Long-Distance Efficiency"
    },
    "sections": [
      {
        "type": "intro-accent",
        "heading": "Long-Distance Efficiency",
        "paragraphs": [
          "Rail transport is one of the most reliable and sustainable methods for transporting goods, especially over long distances.",
          "Atlant Logistics & Relocations offers international rail transport for bulk, palletized, and containerized cargo. Suitable for large volumes with stable schedules and optimal costs. We provide combined services with trucks and containers for intermediate deliveries.",
          "We work with reliable European and international rail operators, ensuring traceability, security, and ecological advantages."
        ]
      },
      {
        "type": "service-topics",
        "label": "Useful tips",
        "heading": "Everything you need to know about Rail Transport",
        "topics": [
          {
            "title": "Features in Planning Rail Transport",
            "intro": "Rail transport has its own logic, different from “order a truck for tomorrow”:",
            "points": [
              {
                "title": "Schedules and slots",
                "text": "Operates on schedules and slots that are planned in advance."
              },
              {
                "title": "Suitable equipment",
                "text": "Requires suitable loading/unloading equipment – ramps, cranes, silos, conveyors depending on cargo type."
              },
              {
                "title": "International operators",
                "text": "Often involves international operators whose requirements must be synchronized (documents, packaging, safety)."
              }
            ],
            "footer": [
              "A well-planned rail transport can bring significant savings but requires a competent partner familiar with the network and procedures."
            ]
          },
          {
            "title": "Rail transport costs: where savings really happen and where they don't",
            "intro": "Rail transport is often perceived simply as “cheaper than a truck.” Reality is a bit more nuanced:",
            "points": [
              {
                "title": "Where the savings are",
                "text": "For large volumes – entire wagons or block trains."
              },
              {
                "title": "Long distances",
                "text": "Over long distances, where the price per ton/km drops significantly compared to road transport."
              },
              {
                "title": "Regular schedules",
                "text": "With regular schedules, when capacity can be planned and better rates negotiated."
              },
              {
                "title": "Where hidden costs appear if not careful",
                "text": "Loading/unloading operations at terminals (rail → truck and back)."
              },
              {
                "title": "Waiting fees",
                "text": "Waiting fees if documents are incomplete or goods are not ready for acceptance."
              },
              {
                "title": "Non-optimized batches",
                "text": "Non-optimized batches – too small quantities forced into a rail schedule instead of staying on a truck."
              }
            ],
            "footer": []
          }
        ]
      },
      {
        "type": "comparison-table",
        "label": "Comparison",
        "heading": "Rail vs. Road Transport Advantages Table",
        "columns": [
          "Criterion",
          "Rail transport",
          "Road transport"
        ],
        "rows": [
          {
            "criterion": "Transport cost",
            "left": "Lower for large volumes and long distances.",
            "right": "Higher, especially over long distances."
          },
          {
            "criterion": "Capacity and volume",
            "left": "Suitable for large and heavy goods (bulk, containers, tanks).",
            "right": "Limited by truck capacity and road infrastructure."
          },
          {
            "criterion": "Energy efficiency",
            "left": "More efficient and eco-friendly, with lower fuel consumption per ton-kilometer.",
            "right": "Higher fuel consumption and CO₂ emissions."
          },
          {
            "criterion": "Reliability and predictability",
            "left": "High over long distances and fixed routes.",
            "right": "Dependent on traffic, road conditions, and regulations."
          },
          {
            "criterion": "Environmental impact",
            "left": "Lower, with less noise and fewer emissions.",
            "right": "Higher pollution and noise in urban areas."
          },
          {
            "criterion": "Suitable cargo types",
            "left": "Bulk goods, containers, raw materials, heavy machinery.",
            "right": "Palletized goods, small parcels, perishable goods."
          },
          {
            "criterion": "International transport",
            "left": "Excellent for transit and large volumes along certain corridors (TEN-T).",
            "right": "Flexible but limited by customs, traffic, and road restrictions."
          },
          {
            "criterion": "Cargo security",
            "left": "High, with fewer accidents and thefts.",
            "right": "Lower, with more road accidents and transport risks."
          }
        ]
      }
    ]
  },
  "ru": {
    "meta": {
      "title": "Железнодорожный транспорт | Atlant Logistics",
      "description": "Эффективность на дальние расстояния"
    },
    "hero": {
      "label": "Atlant Logistics",
      "title": "Железнодорожный транспорт",
      "subtitle": "Эффективность на дальние расстояния"
    },
    "sections": [
      {
        "type": "intro-accent",
        "heading": "Эффективность на дальние расстояния",
        "paragraphs": [
          "Железнодорожный транспорт является одним из самых надёжных и устойчивых способов перевозки грузов, особенно на большие расстояния.",
          "Atlant Logistics & Relocations предлагает международные железнодорожные перевозки для насыпных, палетизированных и контейнерных грузов. Подходит для больших объёмов со стабильным графиком и оптимальными затратами. При необходимости выполняем комбинированные услуги с автомобильным транспортом и контейнерами для промежуточных доставок.",
          "Мы работаем с надёжными европейскими и международными железнодорожными операторами, обеспечивая отслеживаемость, безопасность и экологические преимущества."
        ]
      },
      {
        "type": "service-topics",
        "label": "Полезные советы",
        "heading": "Всё, что нужно знать о Железнодорожном транспорте",
        "topics": [
          {
            "title": "Особенности планирования",
            "intro": "ЖД транспорт работает по своей логике:",
            "points": [
              {
                "title": "Графики и слоты",
                "text": "Планирование по расписаниям."
              },
              {
                "title": "Подходящее оборудование",
                "text": "Необходимость спецоборудования."
              },
              {
                "title": "Международные операторы",
                "text": "Синхронизация международных операторов."
              }
            ],
            "footer": [
              "Грамотное планирование дает экономию."
            ]
          },
          {
            "title": "Стоимость ЖД перевозок",
            "intro": "Реальность сложнее, чем «дешевле грузовика».",
            "points": [
              {
                "title": "Где достигается экономия",
                "text": "Большие объемы."
              },
              {
                "title": "Длинные расстояния",
                "text": "Дальние расстояния."
              },
              {
                "title": "Регулярные графики",
                "text": "Регулярные отправки."
              },
              {
                "title": "Где возникают скрытые расходы, если не учитывать нюансы",
                "text": "Терминальные операции."
              },
              {
                "title": "Сборы за простой",
                "text": "Простои."
              },
              {
                "title": "Неоптимизированные партии",
                "text": "Неоптимальные партии."
              }
            ],
            "footer": []
          }
        ]
      },
      {
        "type": "comparison-table",
        "label": "Сравнение",
        "heading": "Сравнение ЖД и автоперевозок",
        "columns": [
          "Критерий",
          "ЖД транспорт",
          "Автотранспорт"
        ],
        "rows": [
          {
            "criterion": "Стоимость перевозки",
            "left": "Ниже при больших объемах",
            "right": "Выше на дальние расстояния"
          },
          {
            "criterion": "Вместимость",
            "left": "Большие и тяжелые грузы",
            "right": "Ограничена грузовиком"
          },
          {
            "criterion": "Энергоэффективность",
            "left": "Более экологично",
            "right": "Выше выбросы"
          },
          {
            "criterion": "Надежность",
            "left": "Высокая",
            "right": "Зависит от дорог"
          },
          {
            "criterion": "Экология",
            "left": "Низкие выбросы",
            "right": "Высокий шум и загрязнение"
          },
          {
            "criterion": "Типы грузов",
            "left": "Сырье, контейнеры, техника",
            "right": "Паллеты, скоропорт"
          },
          {
            "criterion": "Международные перевозки",
            "left": "Эффективно по коридорам",
            "right": "Ограничения по дорогам"
          },
          {
            "criterion": "Безопасность",
            "left": "Высокая",
            "right": "Ниже"
          }
        ]
      }
    ]
  }
}
